typeshi/__init__.py
typeshi/cls.py
typeshi/jsonf.py
typeshi/str_repr.py
typeshi/util.py
typeshi/version.py
typeshi-2.0.1.dist-info/LICENSE
typeshi-2.0.1.dist-info/METADATA
typeshi-2.0.1.dist-info/WHEEL
typeshi-2.0.1.dist-info/top_level.txt
typeshi-2.0.1.dist-info/RECORD
