Metadata-Version: 2.1
Name: typeshi
Version: 2.0.1
Summary: Easy-to-use TypedDict generation utilities
Home-page: https://github.com/seven7ty/typeshi
Author: Paul Przybyszewski
Author-email: paul@przybyszew.ski
License: MIT
Classifier: Programming Language :: Python :: 3
Classifier: License :: OSI Approved :: MIT License
Requires-Python: >=3.11
License-File: LICENSE
Requires-Dist: frozendict
